yalp_grok/__init__.py
yalp_grok/exceptions.py
yalp_grok/version.py
yalp_grok/yalp_grok.py
yalp_grok/patterns/firewalls
yalp_grok/patterns/grok-patterns
yalp_grok/patterns/haproxy
yalp_grok/patterns/java
yalp_grok/patterns/junos
yalp_grok/patterns/linux-syslog
yalp_grok/patterns/mcollective
yalp_grok/patterns/mcollective-patterns
yalp_grok/patterns/nagios
yalp_grok/patterns/postgresql
yalp_grok/patterns/redis
yalp_grok/patterns/ruby
yalp_grok-0.3.dist-info/top_level.txt
yalp_grok-0.3.dist-info/METADATA
yalp_grok-0.3.dist-info/DESCRIPTION.rst
yalp_grok-0.3.dist-info/metadata.json
yalp_grok-0.3.dist-info/WHEEL
yalp_grok-0.3.dist-info/RECORD
