Metadata-Version: 2.0
Name: yalp-grok
Version: 0.3
Summary: A Python library to parse strings and extract information from structured/unstructured data
Home-page: https://github.com/yalp/yalp-grok
Author: Timothy Messier
Author-email: tim.messier@gmail.com
License: MIT
Platform: UNKNOWN
Classifier: Programming Language :: Python
Classifier: Programming Language :: Python :: 2.7
Requires-Dist: regex (>=2015.07.19)
